LICENSE
README.rst
setup.cfg
setup.py
jf/__init__.py
jf/__main__.py
jf/extra_functions.py
jf/jfio.py
jf/jsonlgen.cc
jf/main.py
jf/meta.py
jf/process.py
jf/query_parser.py
jf.egg-info/PKG-INFO
jf.egg-info/SOURCES.txt
jf.egg-info/dependency_links.txt
jf.egg-info/entry_points.txt
jf.egg-info/requires.txt
jf.egg-info/top_level.txt
jf.egg-info/zip-safe