Metadata-Version: 2.1
Name: jf
Version: 1.1.2
Summary: Python jsonl query engine
Home-page: https://github.com/alhoo/jf
Download-URL: https://github.com/alhoo/jf/archive/1.1.2.tar.gz
Author: Lasse Hyyrynen
Author-email: lasse.hyyrynen@pm.me
Maintainer: Lasse Hyyrynen
Maintainer-email: lasse.hyyrynen@pm.me
License: MIT
Keywords: json,jsonl,yaml,jq
Platform: UNKNOWN
Classifier: Development Status :: 4 - Beta
Classifier: Intended Audience :: Developers
Classifier: Intended Audience :: Science/Research
Classifier: License :: OSI Approved :: MIT License
Classifier: Programming Language :: Python :: 3
Classifier: Topic :: Utilities
Provides-Extra: dev
License-File: LICENSE
